s3_site_maker/__init__.py
s3_site_maker/aws_controller.py
s3_site_maker/cli.py
s3_site_maker/core.py
s3_site_maker-0.0.5.dist-info/METADATA
s3_site_maker-0.0.5.dist-info/RECORD
s3_site_maker-0.0.5.dist-info/WHEEL
s3_site_maker-0.0.5.dist-info/entry_points.txt
s3_site_maker-0.0.5.dist-info/top_level.txt
