Metadata-Version: 2.1
Name: s3-site-maker
Version: 0.0.5
Summary: Create a static webstie in an S3 Bucket
Home-page: UNKNOWN
Author: Alberto Acuna
Author-email: aacuna3@asu.edu
License: MIT License
Platform: UNKNOWN
Classifier: Environment :: Console
Classifier: License :: OSI Approved :: Apache Software License
Classifier: Operating System :: OS Independent
Classifier: Programming Language :: Python
Classifier: Programming Language :: Python :: 3.6
Classifier: Topic :: Internet :: WWW/HTTP
Classifier: Topic :: Internet :: WWW/HTTP :: Dynamic Content
Requires-Dist: boto3 (==1.7.73)
Requires-Dist: botocore (==1.10.73)
Requires-Dist: cement (==2.10.12)
Requires-Dist: docutils (==0.14)
Requires-Dist: jmespath (==0.9.3)
Requires-Dist: python-dateutil (==2.7.3)
Requires-Dist: s3transfer (==0.1.13)
Requires-Dist: six (==1.11.0)
